pobapi/__init__.py
pobapi/api.py
pobapi/async_util.py
pobapi/build_builder.py
pobapi/build_modifier.py
pobapi/builders.py
pobapi/cache.py
pobapi/config.py
pobapi/constants.py
pobapi/crafting.py
pobapi/decorators.py
pobapi/exceptions.py
pobapi/factory.py
pobapi/interfaces.py
pobapi/model_validators.py
pobapi/models.py
pobapi/parsers_compat.py
pobapi/serializers.py
pobapi/stats.py
pobapi/trade.py
pobapi/types.py
pobapi/util.py
pobapi/validators.py
pobapi/calculator/__init__.py
pobapi/calculator/conditional.py
pobapi/calculator/config_modifier_parser.py
pobapi/calculator/damage.py
pobapi/calculator/defense.py
pobapi/calculator/engine.py
pobapi/calculator/game_data.py
pobapi/calculator/item_modifier_parser.py
pobapi/calculator/jewel_parser.py
pobapi/calculator/legion_jewels.py
pobapi/calculator/minion.py
pobapi/calculator/mirage.py
pobapi/calculator/modifiers.py
pobapi/calculator/pantheon.py
pobapi/calculator/party.py
pobapi/calculator/passive_tree_parser.py
pobapi/calculator/penetration.py
pobapi/calculator/resource.py
pobapi/calculator/skill_modifier_parser.py
pobapi/calculator/skill_stats.py
pobapi/calculator/unique_item_parser.py
pobapi/calculator/unique_items_extended.py
pobapi/parsers/__init__.py
pobapi/parsers/item_modifier.py
pobapi/parsers/xml.py
pobapi_extended-1.3.0.dist-info/METADATA
pobapi_extended-1.3.0.dist-info/WHEEL
pobapi_extended-1.3.0.dist-info/licenses/LICENSE.txt
pobapi_extended-1.3.0.dist-info/RECORD
