Metadata-Version: 2.4
Name: pobapi-extended
Version: 1.3.0
Summary: API for Path Of Building's build sharing format.
Project-URL: Homepage, https://github.com/ppoelzl/PathOfBuildingAPI
Project-URL: Documentation, https://pobapi.readthedocs.io
Project-URL: Repository, https://github.com/ppoelzl/PathOfBuildingAPI
Project-URL: Issues, https://github.com/ppoelzl/PathOfBuildingAPI/issues
Author-email: Peter Pölzl <33464174+ppoelzl@users.noreply.github.com>
Maintainer-email: Peter Pölzl <33464174+ppoelzl@users.noreply.github.com>, Ravil Shakerov <xellaopromaster@yandex.ru>
License: MIT
License-File: LICENSE.txt
Keywords: pathofbuilding,pathofexile,pob,poe
Classifier: Development Status :: 4 - Beta
Classifier: Intended Audience :: Developers
Classifier: License :: OSI Approved :: MIT License
Classifier: Programming Language :: Python :: 3
Classifier: Programming Language :: Python :: 3.13
Classifier: Topic :: Documentation :: Sphinx
Classifier: Topic :: Games/Entertainment
Classifier: Topic :: Software Development :: Libraries
Classifier: Topic :: Text Processing :: Markup :: XML
Requires-Python: >=3.12
Requires-Dist: lupa>=2.6
Requires-Dist: lxml>=4.6.2
Requires-Dist: requests>=2.25.1
Requires-Dist: six>=1.17.0
Provides-Extra: async
Requires-Dist: aiohttp>=3.8.0; extra == 'async'
Provides-Extra: dev
Requires-Dist: pre-commit>=4.4.0; extra == 'dev'
Provides-Extra: docs
Requires-Dist: sphinx-autodoc-typehints>=1.11.1; extra == 'docs'
Requires-Dist: sphinx<5.0.0,>=3.4.2; extra == 'docs'
Provides-Extra: full
Requires-Dist: aiohttp>=3.8.0; extra == 'full'
Requires-Dist: freezegun>=1.5.5; extra == 'full'
Requires-Dist: lxml>=4.6.2; extra == 'full'
Requires-Dist: mypy>=1.4.1; extra == 'full'
Requires-Dist: pre-commit>=4.4.0; extra == 'full'
Requires-Dist: pytest-asyncio>=0.21.0; extra == 'full'
Requires-Dist: pytest-cov>=4.1.0; extra == 'full'
Requires-Dist: pytest-mock>=3.11.1; extra == 'full'
Requires-Dist: pytest-xdist>=3.5.0; extra == 'full'
Requires-Dist: pytest>=7.4.4; extra == 'full'
Requires-Dist: requests>=2.25.1; extra == 'full'
Requires-Dist: ruff>=0.14.4; extra == 'full'
Requires-Dist: sphinx-autodoc-typehints>=1.11.1; extra == 'full'
Requires-Dist: sphinx<5.0.0,>=3.4.2; extra == 'full'
Provides-Extra: linters-typers
Requires-Dist: mypy>=1.4.1; extra == 'linters-typers'
Requires-Dist: ruff>=0.14.4; extra == 'linters-typers'
Provides-Extra: test
Requires-Dist: freezegun>=1.5.5; extra == 'test'
Requires-Dist: pytest-asyncio>=0.21.0; extra == 'test'
Requires-Dist: pytest-cov>=4.1.0; extra == 'test'
Requires-Dist: pytest-mock>=3.11.1; extra == 'test'
Requires-Dist: pytest-xdist>=3.5.0; extra == 'test'
Requires-Dist: pytest>=7.4.4; extra == 'test'
